StatisticVibes/correlation.py
StatisticVibes-0.1.dist-info/METADATA
StatisticVibes-0.1.dist-info/WHEEL
StatisticVibes-0.1.dist-info/top_level.txt
StatisticVibes-0.1.dist-info/RECORD
