Metadata-Version: 2.1
Name: StatisticVibes
Version: 0.1
Summary: this is a package
Author: Abdul Sami
License: UNKNOWN
Platform: UNKNOWN
